wealth_os/__init__.py
wealth_os/__main__.py
wealth_os/api/server.py
wealth_os/cli/__init__.py
wealth_os/cli/account.py
wealth_os/cli/chart.py
wealth_os/cli/context_cmd.py
wealth_os/cli/export_cmd.py
wealth_os/cli/import_cmd.py
wealth_os/cli/report.py
wealth_os/cli/tx.py
wealth_os/cli/ui.py
wealth_os/core/config.py
wealth_os/core/context.py
wealth_os/core/valuation.py
wealth_os/datasources/__init__.py
wealth_os/datasources/base.py
wealth_os/datasources/coindesk_legacy.py
wealth_os/datasources/coinmarketcap.py
wealth_os/datasources/generic_csv.py
wealth_os/datasources/registry.py
wealth_os/db/__init__.py
wealth_os/db/engine.py
wealth_os/db/models.py
wealth_os/db/repo.py
wealth_os/io/charts.py
wealth_os/io/pdf_report.py
wealth_os/ui/.gitignore
wealth_os/ui/README.md
wealth_os/ui/components.json
wealth_os/ui/eslint.config.mjs
wealth_os/ui/next.config.ts
wealth_os/ui/package-lock.json
wealth_os/ui/package.json
wealth_os/ui/postcss.config.mjs
wealth_os/ui/tsconfig.json
wealth_os/ui/app/favicon.ico
wealth_os/ui/app/globals.css
wealth_os/ui/app/layout.tsx
wealth_os/ui/app/page.tsx
wealth_os/ui/app/accounts/page.tsx
wealth_os/ui/app/accounts/[id]/page.tsx
wealth_os/ui/app/settings/page.tsx
wealth_os/ui/app/transactions/page.tsx
wealth_os/ui/components/account-multi-select.tsx
wealth_os/ui/components/add-transaction-dialog.tsx
wealth_os/ui/components/app-sidebar.tsx
wealth_os/ui/components/chart-area-interactive.tsx
wealth_os/ui/components/create-account-dialog.tsx
wealth_os/ui/components/dashboard-provider.tsx
wealth_os/ui/components/data-table.tsx
wealth_os/ui/components/edit-account-dialog.tsx
wealth_os/ui/components/edit-transaction-dialog.tsx
wealth_os/ui/components/nav-documents.tsx
wealth_os/ui/components/nav-main.tsx
wealth_os/ui/components/nav-secondary.tsx
wealth_os/ui/components/nav-user.tsx
wealth_os/ui/components/page-transition.tsx
wealth_os/ui/components/section-cards.tsx
wealth_os/ui/components/site-header.tsx
wealth_os/ui/components/theme-toggle.tsx
wealth_os-0.1.2.dist-info/METADATA
wealth_os-0.1.2.dist-info/WHEEL
wealth_os-0.1.2.dist-info/entry_points.txt
wealth_os-0.1.2.dist-info/licenses/LICENSE
wealth_os-0.1.2.dist-info/RECORD
