Metadata-Version: 2.4
Name: wealth-os
Version: 0.1.2
Summary: A comprehensive open-source wealth management tool.
Author-email: chandralegend <irugalbandarachandra@gmail.com>
License-File: LICENSE
Requires-Python: >=3.11
Requires-Dist: fastapi>=0.115.0
Requires-Dist: pandas>=2.3.3
Requires-Dist: pillow>=12.0.0
Requires-Dist: plotext>=5.3.2
Requires-Dist: pytest>=8.4.2
Requires-Dist: python-dotenv>=1.0.1
Requires-Dist: python-multipart>=0.0.20
Requires-Dist: reportlab>=4.4.4
Requires-Dist: requests>=2.32.5
Requires-Dist: rich>=14.2.0
Requires-Dist: seaborn>=0.13.2
Requires-Dist: sqlmodel>=0.0.27
Requires-Dist: typer>=0.19.2
Requires-Dist: uvicorn>=0.30.6
